{
  "_doc": "List of famous traders to add as figures. Each entry needs:\n  - slug: kebab-case unique id\n  - display_name: how it shows on the page\n  - twitter_handle: their X handle (no @)\n  - identifier: either an ENS name (foo.eth) OR a 0x... address OR a Solana base58 address\n  - description: 1-2 sentences\n  - category: one of person | company | government | protocol | celebrity\n\nThe verifier script (scripts/verify-and-sync-traders.mjs) will:\n  1. Resolve each ENS name on-chain via Cloudflare's public Ethereum gateway\n  2. SKIP entries that don't resolve (cannot be verified)\n  3. Upsert verified entries into curated_entities\n\nADD MORE ENTRIES HERE — the script handles the rest.",
  "traders": [
    { "slug": "tetranode", "display_name": "Tetranode", "twitter_handle": "Tetranode", "identifier": "tetranode.eth", "category": "person", "description": "Pseudonymous DeFi whale. Large early holder of LOOKS, RPL and DAO governance tokens." },
    { "slug": "machibigbrother", "display_name": "Machi Big Brother", "twitter_handle": "machibigbrother", "identifier": "machibigbrother.eth", "category": "person", "description": "Jeffrey Huang. Taiwanese musician turned crypto whale; known for high-volume NFT and memecoin trades." },
    { "slug": "pranksy", "display_name": "Pranksy", "twitter_handle": "pranksy", "identifier": "pranksy.eth", "category": "person", "description": "Major NFT collector and trader since 2018." },
    { "slug": "punk6529", "display_name": "6529", "twitter_handle": "punk6529", "identifier": "punk6529.eth", "category": "person", "description": "Pseudonymous NFT thinker and large CryptoPunks holder (Punk #6529)." },
    { "slug": "dingaling", "display_name": "Dingaling", "twitter_handle": "dingalingts", "identifier": "dingaling.eth", "category": "person", "description": "Major NFT collector and OpenSea power-user since 2018." },
    { "slug": "beanie", "display_name": "Beanie", "twitter_handle": "beaniemaxi", "identifier": "beaniemaxi.eth", "category": "person", "description": "NFT collector and early Bored Apes holder." },
    { "slug": "fvckrender", "display_name": "Fvckrender", "twitter_handle": "fvckrender", "identifier": "fvckrender.eth", "category": "person", "description": "3D digital artist and prominent NFT collector." },
    { "slug": "loomdart", "display_name": "Loomdart", "twitter_handle": "loomdart", "identifier": "loomdart.eth", "category": "person", "description": "Veteran trader from eGirl Capital, active on Ethereum since pre-DeFi-summer." },
    { "slug": "0xsisyphus", "display_name": "0xSisyphus", "twitter_handle": "0xSisyphus", "identifier": "0xsisyphus.eth", "category": "person", "description": "Pseudonymous DeFi/perp trader, ex-Genesis." },
    { "slug": "smolting", "display_name": "Smolting", "twitter_handle": "smolting", "identifier": "smolting.eth", "category": "person", "description": "DeFi user known for Aave / Compound / GMX positions." },
    { "slug": "degenspartan", "display_name": "DegenSpartan", "twitter_handle": "degenspartan", "identifier": "degenspartan.eth", "category": "person", "description": "Pseudonymous DeFi-era trader and commentator." },
    { "slug": "andrew-kang", "display_name": "Andrew Kang", "twitter_handle": "Rewkang", "identifier": "rewkang.eth", "category": "person", "description": "Co-founder Mechanism Capital. Active perp and altcoin trader." },
    { "slug": "su-zhu", "display_name": "Su Zhu", "twitter_handle": "zhusu", "identifier": "zhusu.eth", "category": "person", "description": "Co-founder of Three Arrows Capital (defunct)." },
    { "slug": "kain-warwick", "display_name": "Kain Warwick", "twitter_handle": "kaiynne", "identifier": "kain.eth", "category": "person", "description": "Founder of Synthetix and Infinex." },
    { "slug": "stani-kulechov", "display_name": "Stani Kulechov", "twitter_handle": "StaniKulechov", "identifier": "stani.eth", "category": "person", "description": "Founder of Aave." },
    { "slug": "kyle-davies", "display_name": "Kyle Davies", "twitter_handle": "kyled116", "identifier": "kyle.eth", "category": "person", "description": "Co-founder of Three Arrows Capital (defunct)." },
    { "slug": "anthony-sassano", "display_name": "Anthony Sassano", "twitter_handle": "sassal0x", "identifier": "sassal.eth", "category": "person", "description": "Ethereum educator, host of The Daily Gwei." },
    { "slug": "ryan-sean-adams", "display_name": "Ryan Sean Adams", "twitter_handle": "RyanSAdams", "identifier": "ryan.bankless.eth", "category": "person", "description": "Co-founder of Bankless." },

    { "slug": "hsaka", "display_name": "Hsaka", "twitter_handle": "HsakaTrades", "identifier": "hsaka.eth", "category": "person", "description": "Pseudonymous trader and chartist. One of the most-followed crypto TA accounts." },
    { "slug": "cobie-2", "display_name": "Cobie (cobie.eth)", "twitter_handle": "cobie", "identifier": "cobie.eth", "category": "person", "description": "Jordan Fish — UpOnly podcast co-host, ex-Bitmex investor. cobie.eth main." },
    { "slug": "ledger-status", "display_name": "Ledger Status", "twitter_handle": "ledgerstatus", "identifier": "ledgerstatus.eth", "category": "person", "description": "Veteran crypto trader and educator." },
    { "slug": "crypto-cobain", "display_name": "Cobain", "twitter_handle": "Crypto_Cobain", "identifier": "cryptocobain.eth", "category": "person", "description": "Pseudonymous trader, founder of CT-resident @Crypto_Cobain." },
    { "slug": "alex-svanevik", "display_name": "Alex Svanevik", "twitter_handle": "ASvanevik", "identifier": "svanevik.eth", "category": "person", "description": "CEO of Nansen, on-chain data leader." },
    { "slug": "0xmaki", "display_name": "0xMaki", "twitter_handle": "0xMaki", "identifier": "maki.eth", "category": "person", "description": "Co-founder of SushiSwap, DeFi OG." },
    { "slug": "andre-cronje", "display_name": "Andre Cronje", "twitter_handle": "AndreCronjeTech", "identifier": "andrecronje.eth", "category": "person", "description": "Founder of Yearn Finance, Fantom architect, Sonic Labs." },
    { "slug": "kerman-kohli", "display_name": "Kerman Kohli", "twitter_handle": "kermankohli", "identifier": "kerman.eth", "category": "person", "description": "DeFi educator, founder DeFi Weekly." },
    { "slug": "tyler-reynolds", "display_name": "Tyler Reynolds", "twitter_handle": "TylerDReynolds", "identifier": "tyler.eth", "category": "person", "description": "Crypto investor and writer, formerly at Multicoin." },
    { "slug": "tarun-chitra", "display_name": "Tarun Chitra", "twitter_handle": "tarunchitra", "identifier": "tarun.eth", "category": "person", "description": "Founder of Gauntlet, DeFi risk-modeling firm." },
    { "slug": "robert-leshner", "display_name": "Robert Leshner", "twitter_handle": "rleshner", "identifier": "leshner.eth", "category": "person", "description": "Founder of Compound, now CEO of Superstate." },
    { "slug": "haseeb-qureshi", "display_name": "Haseeb Qureshi", "twitter_handle": "hosseeb", "identifier": "haseeb.eth", "category": "person", "description": "Managing partner at Dragonfly Capital." },
    { "slug": "fabda", "display_name": "fabda", "twitter_handle": "fabdaprince", "identifier": "fabda.eth", "category": "person", "description": "DeFi trader and investor." },
    { "slug": "hayden-z-adams", "display_name": "Hayden Adams (haydenzadams.eth)", "twitter_handle": "haydenzadams", "identifier": "haydenzadams.eth", "category": "person", "description": "Founder of Uniswap." },
    { "slug": "garyvee", "display_name": "Gary Vaynerchuk", "twitter_handle": "garyvee", "identifier": "garyvee.eth", "category": "celebrity", "description": "Entrepreneur, NFT collector and creator of VeeFriends." },
    { "slug": "deeze", "display_name": "Deeze", "twitter_handle": "deezefi", "identifier": "deeze.eth", "category": "person", "description": "DeFi trader and degen, prominent on CT." },
    { "slug": "joe-mccann", "display_name": "Joe McCann", "twitter_handle": "joemccann", "identifier": "joemccann.eth", "category": "person", "description": "Founder of Asymmetric, ex-Microsoft." },
    { "slug": "santiago-r-santos", "display_name": "Santiago R Santos", "twitter_handle": "santiagoroel", "identifier": "santiagosantos.eth", "category": "person", "description": "Crypto investor, ex-ParaFi." },
    { "slug": "0xngmi", "display_name": "0xngmi", "twitter_handle": "0xngmi", "identifier": "0xngmi.eth", "category": "person", "description": "DefiLlama founder, on-chain data." },
    { "slug": "willyogo", "display_name": "Willy Woo", "twitter_handle": "woonomic", "identifier": "willyogo.eth", "category": "person", "description": "On-chain Bitcoin analyst." },
    { "slug": "scoopy-trooples", "display_name": "Scoopy Trooples", "twitter_handle": "scupytrooples", "identifier": "scoopytrooples.eth", "category": "person", "description": "Founder of Alchemix, DeFi protocol designer." },
    { "slug": "matthew-graham", "display_name": "Matthew Graham", "twitter_handle": "mattysino", "identifier": "matthewgraham.eth", "category": "person", "description": "Founder of Sino Global Capital." },
    { "slug": "mr-block", "display_name": "Mister Block", "twitter_handle": "MisterBlock", "identifier": "misterblock.eth", "category": "person", "description": "DeFi trader and writer." },
    { "slug": "danny-ryan", "display_name": "Danny Ryan", "twitter_handle": "dannyryan", "identifier": "dannyryan.eth", "category": "person", "description": "Ethereum Foundation researcher, beacon chain." },
    { "slug": "justin-drake", "display_name": "Justin Drake", "twitter_handle": "drakefjustin", "identifier": "drakefjustin.eth", "category": "person", "description": "Ethereum Foundation researcher, danksharding designer." },
    { "slug": "sreeram-kannan", "display_name": "Sreeram Kannan", "twitter_handle": "sreeramkannan", "identifier": "sreeram.eth", "category": "person", "description": "Founder of EigenLayer." },
    { "slug": "guy-young", "display_name": "Guy Young", "twitter_handle": "leptokurtic_", "identifier": "guy.eth", "category": "person", "description": "Founder of Ethena Labs (USDe)." },
    { "slug": "sandeep-nailwal", "display_name": "Sandeep Nailwal", "twitter_handle": "sandeepnailwal", "identifier": "sandeep.eth", "category": "person", "description": "Co-founder of Polygon." },
    { "slug": "anatoly-yakovenko", "display_name": "Anatoly Yakovenko", "twitter_handle": "aeyakovenko", "identifier": "toly.eth", "category": "person", "description": "Co-founder of Solana Labs." },
    { "slug": "mert-mumtaz", "display_name": "Mert Mumtaz", "twitter_handle": "0xMert_", "identifier": "mert.eth", "category": "person", "description": "CEO of Helius (Solana RPC)." },
    { "slug": "raoul-pal", "display_name": "Raoul Pal", "twitter_handle": "RaoulGMI", "identifier": "raoulpal.eth", "category": "person", "description": "Founder of Real Vision, macro investor." },
    { "slug": "mike-novogratz", "display_name": "Mike Novogratz", "twitter_handle": "novogratz", "identifier": "novogratz.eth", "category": "person", "description": "Founder of Galaxy Digital." },
    { "slug": "arthur-hayes", "display_name": "Arthur Hayes", "twitter_handle": "CryptoHayes", "identifier": "arthurhayes.eth", "category": "person", "description": "Co-founder of BitMEX, prolific essayist on macro." },
    { "slug": "do-kwon", "display_name": "Do Kwon", "twitter_handle": "stablekwon", "identifier": "dokwon.eth", "category": "person", "description": "Founder of Terraform Labs (Terra/LUNA collapse)." },
    { "slug": "cz-binance", "display_name": "Changpeng Zhao", "twitter_handle": "cz_binance", "identifier": "cz.eth", "category": "person", "description": "Founder of Binance." },
    { "slug": "brian-armstrong", "display_name": "Brian Armstrong", "twitter_handle": "brian_armstrong", "identifier": "brianarmstrong.eth", "category": "person", "description": "Co-founder and CEO of Coinbase." },
    { "slug": "jesse-pollak", "display_name": "Jesse Pollak", "twitter_handle": "jessepollak", "identifier": "jesse.base.eth", "category": "person", "description": "Creator of Base (Coinbase L2)." },
    { "slug": "punk4156", "display_name": "punk4156", "twitter_handle": "punk4156", "identifier": "punk4156.eth", "category": "person", "description": "Founder of Nouns DAO, anon CryptoPunks holder." },
    { "slug": "ricmoo", "display_name": "Richard Moore (ricmoo)", "twitter_handle": "ricmoo", "identifier": "ricmoo.eth", "category": "person", "description": "Author of ethers.js." },
    { "slug": "nick-johnson", "display_name": "Nick Johnson", "twitter_handle": "nicksdjohnson", "identifier": "nick.eth", "category": "person", "description": "Founder of ENS." },
    { "slug": "preston-vanloon", "display_name": "Preston Van Loon", "twitter_handle": "preston_vanloon", "identifier": "prestonvanloon.eth", "category": "person", "description": "Co-founder of Prysmatic Labs (Prysm consensus client)." },
    { "slug": "phil-daian", "display_name": "Phil Daian", "twitter_handle": "phildaian", "identifier": "phildaian.eth", "category": "person", "description": "Flashbots co-founder, MEV researcher." }
  ]
}
